category_equations/__init__.py
category_equations/analysis.py
category_equations/category.py
category_equations/operation.py
category_equations/processed_term.py
category_equations/term.py
python_category_equations-0.8.0.dist-info/LICENSE
python_category_equations-0.8.0.dist-info/METADATA
python_category_equations-0.8.0.dist-info/WHEEL
python_category_equations-0.8.0.dist-info/top_level.txt
python_category_equations-0.8.0.dist-info/RECORD
