Metadata-Version: 2.1
Name: python-category-equations
Version: 0.8.0
Summary: python-category-equations
Home-page: https://github.com/kummahiih/python-category-equations
Author: Pauli Rikula
License: MIT
Classifier: License :: OSI Approved :: MIT License
Classifier: Programming Language :: Python :: 3.6
Requires-Python: ~=3.6
License-File: LICENSE
